pyqpanda/__init__.py
pyqpanda/optimizerTest.py
pyqpanda/pyQPanda.cpython-310-x86_64-linux-gnu.so
pyqpanda/pyQPanda.pyi
pyqpanda/utils.py
pyqpanda/Algorithm/__init__.py
pyqpanda/Algorithm/fragments.py
pyqpanda/Algorithm/hamiltonian_simulation.py
pyqpanda/Algorithm/QuantumCircuitLearning/__init__.py
pyqpanda/Algorithm/QuantumCircuitLearning/quantum_circuit_learning.py
pyqpanda/Algorithm/QuantumGradient/__init__.py
pyqpanda/Algorithm/QuantumGradient/quantum_gradient.py
pyqpanda/Algorithm/QuantumGradient/quantum_gradient_qaoa_test.py
pyqpanda/Algorithm/VariationalQuantumEigensolver/__init__.py
pyqpanda/Algorithm/VariationalQuantumEigensolver/vqe.py
pyqpanda/Algorithm/demo/Deustch_Jozsa.py
pyqpanda/Algorithm/demo/Grover.py
pyqpanda/Algorithm/demo/__init__.py
pyqpanda/Algorithm/test/__init__.py
pyqpanda/Algorithm/test/hamiltonian_simulation_test.py
pyqpanda/Algorithm/test/qaoa_maxcut_test.py
pyqpanda/Algorithm/test/qaoa_test.py
pyqpanda/Algorithm/test/qcl_test.py
pyqpanda/Algorithm/test/quantum_gradient_qaoa_test.py
pyqpanda/Algorithm/test/state_preparation_test.py
pyqpanda/Algorithm/test/test_script.py
pyqpanda/Algorithm/test/test_utils.py
pyqpanda/Algorithm/test/vqe_test.py
pyqpanda/Hamiltonian/__init__.py
pyqpanda/Hamiltonian/chemistry_client.py
pyqpanda/Hamiltonian/PauliOperator/__init__.py
pyqpanda/Hamiltonian/test/__init__.py
pyqpanda/Hamiltonian/test/hamiltonian_test.py
pyqpanda/Operator/__init__.py
pyqpanda/Operator/pyQPandaOperator.cpython-310-x86_64-linux-gnu.so
pyqpanda/Operator/pyQPandaOperator.pyi
pyqpanda/OriginService/PilotOSMachine.py
pyqpanda/OriginService/QCloudMachine.py
pyqpanda/OriginService/QCloudPlot.py
pyqpanda/OriginService/__init__.py
pyqpanda/TorchLayer/Torch_.py
pyqpanda/TorchLayer/__init__.py
pyqpanda/TorchLayer/basic_eng.py
pyqpanda/TorchLayer/cir_angle.py
pyqpanda/TorchLayer/torchlayer.py
pyqpanda/Variational/VariationalCircuit.py
pyqpanda/Variational/__init__.py
pyqpanda/Variational/variational_qaoa_citcuit.py
pyqpanda-3.8.5.dist-info/LICENSE
pyqpanda-3.8.5.dist-info/METADATA
pyqpanda-3.8.5.dist-info/WHEEL
pyqpanda-3.8.5.dist-info/top_level.txt
pyqpanda-3.8.5.dist-info/RECORD
