Metadata-Version: 2.2
Name: pyqpanda
Version: 3.8.5
Summary: pyQPanda is Python wrapper of QPanda.
Author: OriginQ
License: Apache Licence
Classifier: Development Status :: 4 - Beta
Classifier: Operating System :: MacOS :: MacOS X
Classifier: Operating System :: Microsoft :: Windows :: Windows 10
Classifier: Operating System :: POSIX :: Linux
Classifier: Topic :: Software Development :: Libraries :: Python Modules
Classifier: Programming Language :: Python
Classifier: Programming Language :: Python :: 3.8
Classifier: Programming Language :: Python :: 3.9
Classifier: Programming Language :: Python :: 3.10
Classifier: Programming Language :: Python :: 3.11
License-File: LICENSE
Requires-Dist: numpy>=1.17
Requires-Dist: matplotlib>=3.7
Requires-Dist: pydot
Requires-Dist: scipy
Requires-Dist: mypy>=1.14
Requires-Dist: requests
Requires-Dist: snowland-smx
Requires-Dist: Cython
Requires-Dist: gmssl
Requires-Dist: networkx
Dynamic: author
Dynamic: classifier
Dynamic: license
Dynamic: requires-dist
Dynamic: summary
